AUTHORS
dd_yandex_pay/__init__.py
dd_yandex_pay/constants.py
dd_yandex_pay/exceptions.py
dd_yandex_pay/yp_client.py
dd_yandex_pay-1.0.1.dist-info/METADATA
dd_yandex_pay-1.0.1.dist-info/WHEEL
dd_yandex_pay-1.0.1.dist-info/licenses/AUTHORS
dd_yandex_pay-1.0.1.dist-info/licenses/LICENSE
dd_yandex_pay-1.0.1.dist-info/RECORD
