Metadata-Version: 2.1
Name: dd_yandex_pay
Version: 1.0.1
Summary: Wrapper for Yandex Pay API.
Project-URL: Documentation, https://dd.github.io/dd_yandex_pay
Project-URL: Repository, https://github.com/dd/dd_yandex_pay
Project-URL: Changelog, https://dd.github.io/dd_yandex_pay/changelog/
Project-URL: Bug Tracker, https://github.com/dd/dd_yandex_pay/issues
Author-email: Dmitry Dobrynin <dd@tovarisch.engineer>
License-Expression: LGPL-3.0
License-File: AUTHORS
License-File: LICENSE
Keywords: payment,yandex,yandex pay
Classifier: Development Status :: 5 - Production/Stable
Classifier: Environment :: Web Environment
Classifier: Intended Audience :: Developers
Classifier: License :: OSI Approved :: GNU Lesser General Public License v3 (LGPLv3)
Classifier: Natural Language :: Russian
Classifier: Operating System :: OS Independent
Classifier: Programming Language :: Python
Classifier: Programming Language :: Python :: 3
Classifier: Programming Language :: Python :: 3 :: Only
Classifier: Programming Language :: Python :: 3.8
Classifier: Programming Language :: Python :: 3.9
Classifier: Programming Language :: Python :: 3.10
Classifier: Programming Language :: Python :: 3.11
Classifier: Programming Language :: Python :: 3.12
Classifier: Programming Language :: Python :: Implementation :: CPython
Classifier: Programming Language :: Python :: Implementation :: PyPy
Classifier: Topic :: Internet :: WWW/HTTP
Classifier: Topic :: Software Development :: Libraries
Classifier: Topic :: Utilities
Requires-Python: >=3.8
Requires-Dist: requests<3,>=2
